pymetheus/__init__.py
pymetheus/decorators.py
pymetheus/method.py
pymetheus/report.py
pymetheus/runner.py
pymetheus/template_generator.py
pymetheus/validators.py
pymetheus/impl/__init__.py
pymetheus/impl/finite_element_2d_impl.py
pyrrha/__init__.py
pyrrha/constants.py
pyrrha/decorators.py
pyrrha/method.py
pyrrha/pyrrha.py
pyrrha/report.py
pyrrha/runner.py
pyrrha/template_generator.py
pyrrha/validators.py
pyrrha/impl/__init__.py
pyrrha/impl/finite_element_2d_impl.py
pyrrha/octave_src/__init__.py
pyrrha/octave_src/fem2d_octave/CHANGELOG.md
pyrrha/octave_src/fem2d_octave/README.md
pyrrha/octave_src/fem2d_octave/__init__.py
pyrrha/octave_src/fem2d_octave/aux_check_dim.m
pyrrha/octave_src/fem2d_octave/aux_check_fn_value.m
pyrrha/octave_src/fem2d_octave/aux_check_module.m
pyrrha/octave_src/fem2d_octave/aux_check_point.m
pyrrha/octave_src/fem2d_octave/aux_check_values.m
pyrrha/octave_src/fem2d_octave/aux_clean_boundary.m
pyrrha/octave_src/fem2d_octave/aux_fem2d_heat_export.m
pyrrha/octave_src/fem2d_octave/aux_find_boundary.m
pyrrha/octave_src/fem2d_octave/aux_find_element.m
pyrrha/octave_src/fem2d_octave/aux_gen_rspd_matrix.m
pyrrha/octave_src/fem2d_octave/aux_mesh_sort.m
pyrrha/octave_src/fem2d_octave/aux_mesh_subd.m
pyrrha/octave_src/fem2d_octave/aux_ts_progress.m
pyrrha/octave_src/fem2d_octave/data_system1.mat
pyrrha/octave_src/fem2d_octave/data_test.mat
pyrrha/octave_src/fem2d_octave/fem2d_heat.m
pyrrha/octave_src/fem2d_octave/fem2d_heat_blerp.m
pyrrha/octave_src/fem2d_octave/fem2d_heat_dirichlet.m
pyrrha/octave_src/fem2d_octave/fem2d_heat_explicit.m
pyrrha/octave_src/fem2d_octave/fem2d_heat_explicit_delta_t.m
pyrrha/octave_src/fem2d_octave/fem2d_heat_flux.m
pyrrha/octave_src/fem2d_octave/fem2d_heat_genC.m
pyrrha/octave_src/fem2d_octave/fem2d_heat_genF.m
pyrrha/octave_src/fem2d_octave/fem2d_heat_genK.m
pyrrha/octave_src/fem2d_octave/fem2d_heat_gen_system.m
pyrrha/octave_src/fem2d_octave/fem2d_heat_graph_mesh.m
pyrrha/octave_src/fem2d_octave/fem2d_heat_implicit.m
pyrrha-0.2.dist-info/LICENSE
pyrrha-0.2.dist-info/METADATA
pyrrha-0.2.dist-info/WHEEL
pyrrha-0.2.dist-info/entry_points.txt
pyrrha-0.2.dist-info/top_level.txt
pyrrha-0.2.dist-info/RECORD
