Metadata-Version: 2.1
Name: pyrrha
Version: 0.2
Summary: pyrrha is a tool for helping in the developement and testing of Computational Mechanics methods.
Home-page: https://gitlab.com/dsklar/pyrrha
Author: ['Diego Sklar', 'Franco Matzkin', 'Constanza Quaglia']
Author-email: dsklar@gmail.com
License: MIT
Keywords: pyrrha
Platform: UNKNOWN
Requires-Dist: numpy
Requires-Dist: oct2py
Requires-Dist: Jinja2
Requires-Dist: typer
